chiefpay/__init__.py
chiefpay/async_client.py
chiefpay/base.py
chiefpay/classes.py
chiefpay/client.py
chiefpay/constants.py
chiefpay/exceptions.py
chiefpay/utils.py
chiefpay/socket/__init__.py
chiefpay/socket/async_client.py
chiefpay/socket/base.py
chiefpay/socket/client.py
chiefpay/types/__init__.py
chiefpay/types/enums.py
chiefpay/types/history.py
chiefpay/types/invoice.py
chiefpay/types/notification.py
chiefpay/types/rates.py
chiefpay/types/transaction.py
chiefpay/types/wallet.py
chiefpay-1.6.0.dist-info/licenses/LICENSE
chiefpay-1.6.0.dist-info/METADATA
chiefpay-1.6.0.dist-info/WHEEL
chiefpay-1.6.0.dist-info/top_level.txt
chiefpay-1.6.0.dist-info/RECORD
